standard_classification/__init__.py
standard_classification/_version.py
standard_classification/get_alphas.py
standard_classification/cls/__init__.py
standard_classification/cls/classify.py
standard_classification-0.1.3b0.dist-info/LICENSE
standard_classification-0.1.3b0.dist-info/METADATA
standard_classification-0.1.3b0.dist-info/WHEEL
standard_classification-0.1.3b0.dist-info/top_level.txt
standard_classification-0.1.3b0.dist-info/RECORD
