Metadata-Version: 2.1
Name: standard_classification
Version: 0.1.3b0
Summary: A tool to classify young stellar objects based on the Lada standard classification.
Author-email: David Hernandez <david.hernandez@univie.ac.at>
Project-URL: Homepage, https://github.com/Starvexx/standard_classification
Project-URL: Documentation, https://standard-classification.readthedocs.io/en/latest/
Requires-Python: >=3.10
License-File: LICENSE
Requires-Dist: numpy >=1.25
Requires-Dist: astropy >=5.3
Requires-Dist: scipy >=1.10
Requires-Dist: tqdm >=4.66
Requires-Dist: matplotlib >=3.8.1
